rapcsv/__init__.py
rapcsv/_rapcsv.cpython-38-x86_64-linux-gnu.so
rapcsv/_rapcsv.pyi
rapcsv/py.typed
rapcsv-0.2.1.dist-info/METADATA
rapcsv-0.2.1.dist-info/WHEEL
rapcsv-0.2.1.dist-info/RECORD
