Metadata-Version: 2.4
Name: rapcsv
Version: 0.2.1
Classifier: Development Status :: 3 - Alpha
Classifier: Intended Audience :: Developers
Classifier: License :: OSI Approved :: MIT License
Classifier: Programming Language :: Python :: 3
Classifier: Programming Language :: Python :: 3.8
Classifier: Programming Language :: Python :: 3.9
Classifier: Programming Language :: Python :: 3.10
Classifier: Programming Language :: Python :: 3.11
Classifier: Programming Language :: Python :: 3.12
Classifier: Programming Language :: Python :: 3.13
Classifier: Programming Language :: Python :: 3.14
Requires-Dist: ruff>=0.1.0 ; extra == 'dev'
Requires-Dist: sphinx>=7.0 ; extra == 'docs'
Requires-Dist: sphinx-rtd-theme>=1.3.0 ; extra == 'docs'
Requires-Dist: myst-parser>=2.0.0 ; extra == 'docs'
Requires-Dist: ruff>=0.1.0 ; extra == 'lint'
Requires-Dist: pytest>=7.0 ; extra == 'test'
Requires-Dist: pytest-asyncio>=0.23.8 ; extra == 'test'
Requires-Dist: pytest-timeout>=2.0 ; extra == 'test'
Requires-Dist: aiocsv>=0.3.0 ; extra == 'test'
Requires-Dist: aiofiles>=23.0 ; extra == 'test'
Requires-Dist: rapfiles>=0.2.1 ; extra == 'test'
Provides-Extra: dev
Provides-Extra: docs
Provides-Extra: lint
Provides-Extra: test
Summary: Streaming async CSV — no fake async, no GIL stalls.
Keywords: async,csv,streaming,async-io
Author: RAP Project
License: MIT
Requires-Python: >=3.8
Project-URL: Documentation, https://rapcsv.readthedocs.io/
Project-URL: Homepage, https://github.com/eddiethedean/rapcsv
Project-URL: Issues, https://github.com/eddiethedean/rapcsv/issues
Project-URL: Repository, https://github.com/eddiethedean/rapcsv
